sora/__init__.py
sora/_sora.py
sora-0.1.1.dist-info/LICENSE
sora-0.1.1.dist-info/METADATA
sora-0.1.1.dist-info/WHEEL
sora-0.1.1.dist-info/top_level.txt
sora-0.1.1.dist-info/RECORD
