Metadata-Version: 2.1
Name: sora
Version: 0.1.1
Summary: A simple and unified library to display images in Jupyter notebooks
Home-page: https://github.com/mznmel/sora
Author: Mazen A. Melibari
Author-email: mazen@mazen.ws
License: MIT
Platform: UNKNOWN
Classifier: Programming Language :: Python :: 3
Classifier: License :: OSI Approved :: MIT License
Classifier: Operating System :: OS Independent
